README.ru.md
img_ops/__init__.py
img_ops/device.py
img_ops/enums.py
img_ops/img_ops.py
img_ops/ops/__init__.py
img_ops/ops/color.py
img_ops/ops/filters.py
img_ops/ops/segm.py
img_ops/py.typed
img_ops/registry.py
img_ops/types.py
img_ops-0.1.1.dist-info/LICENSE
img_ops-0.1.1.dist-info/METADATA
img_ops-0.1.1.dist-info/WHEEL
img_ops-0.1.1.dist-info/RECORD
