Metadata-Version: 2.1
Name: img-ops
Version: 0.1.1
Summary: Device-aware image operations (CPU/GPU/MPS fallback) with a clean Python API for preprocessing tasks.
Home-page: https://github.com/omigutin/img_ops
License: MIT
Keywords: image-processing,image-operations,computer-vision,opencv,cuda,gpu,cpu,preprocessing,ndarray,numpy,contours,segmentation,hsv,gaussian-blur,python-library
Author: migutin83
Author-email: migutin83@yandex.ru
Requires-Python: >=3.10,<3.13
Classifier: Development Status :: 3 - Alpha
Classifier: Intended Audience :: Developers
Classifier: License :: OSI Approved :: MIT License
Classifier: Natural Language :: English
Classifier: Natural Language :: Russian
Classifier: Operating System :: OS Independent
Classifier: Programming Language :: Python
Classifier: Programming Language :: Python :: 3
Classifier: Programming Language :: Python :: 3.10
Classifier: Programming Language :: Python :: 3.11
Classifier: Programming Language :: Python :: 3.12
Classifier: Topic :: Scientific/Engineering :: Image Processing
Classifier: Topic :: Software Development :: Libraries :: Python Modules
Classifier: Typing :: Typed
Requires-Dist: numpy (>=1.26,<2.0)
Requires-Dist: opencv-python (>=4.9,<5.0)
Project-URL: Documentation, https://github.com/omigutin/img_ops#readme
Project-URL: Repository, https://github.com/users/omigutin/projects/4
